specphot/__init__.py
specphot/utils.py
specphot-0.1.1.dist-info/LICENSE
specphot-0.1.1.dist-info/METADATA
specphot-0.1.1.dist-info/WHEEL
specphot-0.1.1.dist-info/top_level.txt
specphot-0.1.1.dist-info/RECORD
